{"v":"4.10.1","fr":29.9700012207031,"ip":83.0000033806593,"op":165.000006720588,"w":1023,"h":643,"nm":"CareCoord Path1 Sec2","ddd":0,"assets":[{"id":"image_0","w":533,"h":50,"u":"images/","p":"img_0.png"},{"id":"image_1","w":117,"h":30,"u":"images/","p":"img_1.png"},{"id":"image_2","w":515,"h":25,"u":"images/","p":"img_2.png"},{"id":"image_3","w":298,"h":123,"u":"images/","p":"img_3.png"},{"id":"image_4","w":300,"h":115,"u":"images/","p":"img_4.png"},{"id":"image_5","w":702,"h":434,"u":"images/","p":"img_5.png"},{"id":"image_6","w":1023,"h":640,"u":"images/","p":"img_6.png"}],"fonts":{"list":[{"fName":"ArialMT","fFamily":"Arial","fStyle":"Regular","ascent":71.5988159179688}]},"layers":[{"ddd":0,"ind":1,"ty":2,"nm":"Path 1 - Section 2- gradientbar.png","cl":"png","refId":"image_0","sr":1,"ks":{"o":{"a":0,"k":100,"ix":11},"r":{"a":0,"k":0,"ix":10},"p":{"a":0,"k":[357.5,93.5,0],"ix":2},"a":{"a":0,"k":[534,27.941,0],"ix":1},"s":{"a":1,"k":[{"i":{"x":[0.833,0.833,0.833],"y":[0.833,0.833,0.833]},"o":{"x":[0.167,0.167,0.167],"y":[0.167,0.167,0.167]},"n":["0p833_0p833_0p167_0p167","0p833_0p833_0p167_0p167","0p833_0p833_0p167_0p167"],"t":0,"s":[40,34,100],"e":[26,34,100]},{"t":25.0000010182709}],"ix":6}},"ao":0,"ip":0,"op":900.000036657751,"st":0,"bm":0},{"ddd":0,"ind":2,"ty":2,"nm":"Path 2 - Search Button Highlight.png","cl":"png","refId":"image_1","sr":1,"ks":{"o":{"a":0,"k":100,"ix":11},"r":{"a":0,"k":0,"ix":10},"p":{"a":0,"k":[384.5,95.5,0],"ix":2},"a":{"a":0,"k":[58.5,15,0],"ix":1},"s":{"a":0,"k":[100,100,100],"ix":6}},"ao":0,"ip":29.0000011811942,"op":79.000003217736,"st":0,"bm":0},{"ddd":0,"ind":3,"ty":2,"nm":"Path 1 - 2 - Heart Failure Symptoms Highlight.png","cl":"png","refId":"image_2","sr":1,"ks":{"o":{"a":0,"k":100,"ix":11},"r":{"a":0,"k":0,"ix":10},"p":{"a":0,"k":[275.5,198.5,0],"ix":2},"a":{"a":0,"k":[257.5,12.5,0],"ix":1},"s":{"a":0,"k":[100,100,100],"ix":6}},"ao":0,"ip":119.000004846969,"op":996.000040567912,"st":96.0000039101602,"bm":0},{"ddd":0,"ind":4,"ty":2,"nm":"Path 1 - Slide 2 - Third Search Section.png","cl":"png","refId":"image_3","sr":1,"ks":{"o":{"a":0,"k":100,"ix":11},"r":{"a":0,"k":0,"ix":10},"p":{"a":0,"k":[864.5,335.5,0],"ix":2},"a":{"a":0,"k":[149,61.5,0],"ix":1},"s":{"a":0,"k":[100,100,100],"ix":6}},"ao":0,"ip":43.0000017514259,"op":999.000040690104,"st":99.0000040323527,"bm":0},{"ddd":0,"ind":5,"ty":2,"nm":"Path 1 - Slide 2 - Second Search Section.png","cl":"png","refId":"image_4","sr":1,"ks":{"o":{"a":0,"k":100,"ix":11},"r":{"a":0,"k":0,"ix":10},"p":{"a":0,"k":[864.5,212.5,0],"ix":2},"a":{"a":0,"k":[150,57.5,0],"ix":1},"s":{"a":0,"k":[100,100,100],"ix":6}},"ao":0,"ip":43.0000017514259,"op":943.000038409177,"st":43.0000017514259,"bm":0},{"ddd":0,"ind":6,"ty":2,"nm":"Path 1 - Slide 2 - First Search Section.png","cl":"png","refId":"image_5","sr":1,"ks":{"o":{"a":0,"k":100,"ix":11},"r":{"a":0,"k":0,"ix":10},"p":{"a":0,"k":[358.5,371.5,0],"ix":2},"a":{"a":0,"k":[351,217,0],"ix":1},"s":{"a":0,"k":[100,100,100],"ix":6}},"ao":0,"ip":43.0000017514259,"op":943.000038409177,"st":43.0000017514259,"bm":0},{"ddd":0,"ind":7,"ty":5,"nm":"heart failure","sr":1,"ks":{"o":{"a":0,"k":100,"ix":11},"r":{"a":0,"k":0,"ix":10},"p":{"a":0,"k":[209.5,97.5,0],"ix":2},"a":{"a":0,"k":[0,0,0],"ix":1},"s":{"a":0,"k":[100,100,100],"ix":6}},"ao":0,"t":{"d":{"k":[{"s":{"s":12,"f":"ArialMT","t":"heart failure","j":1,"tr":0,"lh":14.4,"ls":0,"fc":[0,0,0.01]},"t":0}]},"p":{},"m":{"g":1,"a":{"a":0,"k":[0,0],"ix":2}},"a":[]},"ip":-1.00000004073083,"op":918.000037390907,"st":18.000000733155,"bm":0},{"ddd":0,"ind":8,"ty":2,"nm":"Path 1 - Slide 2 - Blank.png","cl":"png","refId":"image_6","sr":1,"ks":{"o":{"a":0,"k":100,"ix":11},"r":{"a":0,"k":0,"ix":10},"p":{"a":0,"k":[511.5,321.5,0],"ix":2},"a":{"a":0,"k":[511.5,320,0],"ix":1},"s":{"a":0,"k":[100,100,100],"ix":6}},"ao":0,"ip":0,"op":900.000036657751,"st":0,"bm":0}],"chars":[{"ch":"h","size":12,"style":"Regular","w":55.62,"data":{"shapes":[{"ty":"gr","it":[{"ind":0,"ty":"sh","ix":1,"ks":{"a":0,"k":{"i":[[0,0],[0,0],[-0.977,2.312],[-2.295,1.351],[-2.605,0],[-1.904,-2.002],[0,-4.395],[0,0],[0,0],[0,0],[1.221,2.67],[2.832,1.514],[3.841,0],[4.102,-4.752],[0,0],[0,0],[0,0]],"o":[[0,0],[0,-4.069],[0.977,-2.311],[2.295,-1.35],[3.483,0],[1.904,2.002],[0,0],[0,0],[0,0],[0,-5.078],[-1.221,-2.669],[-2.832,-1.514],[-6.25,0],[0,0],[0,0],[0,0],[0,0]],"v":[[15.381,0],[15.381,-28.369],[16.846,-37.939],[21.753,-43.433],[29.102,-45.459],[37.183,-42.456],[40.039,-32.861],[40.039,0],[48.828,0],[48.828,-32.861],[46.997,-44.482],[40.918,-50.757],[30.908,-53.027],[15.381,-45.898],[15.381,-71.582],[6.592,-71.582],[6.592,0]],"c":true},"ix":2},"nm":"h","mn":"ADBE Vector Shape - Group","hd":false}],"nm":"h","np":3,"cix":2,"ix":1,"mn":"ADBE Vector Group","hd":false}]},"fFamily":"Arial"},{"ch":"e","size":12,"style":"Regular","w":55.62,"data":{"shapes":[{"ty":"gr","it":[{"ind":0,"ty":"sh","ix":1,"ks":{"a":0,"k":{"i":[[2.278,-1.692],[3.223,0],[2.897,3.027],[0.325,5.697],[0,0],[0,0.521],[4.395,4.72],[6.934,0],[4.492,-4.817],[0,-8.723],[-4.443,-4.671],[-7.585,0],[-3.874,2.93],[-1.433,5.306],[0,0]],"o":[[-2.279,1.693],[-4.33,0],[-2.898,-3.027],[0,0],[0.032,-1.041],[0,-8.561],[-4.395,-4.72],[-7.162,0],[-4.492,4.818],[0,8.431],[4.443,4.671],[6.022,0],[3.873,-2.93],[0,0],[-1.335,3.711]],"v":[[36.67,-8.594],[28.418,-6.055],[17.578,-10.596],[12.744,-23.682],[51.416,-23.682],[51.465,-26.025],[44.873,-45.947],[27.881,-53.027],[10.4,-45.801],[3.662,-25.488],[10.327,-5.835],[28.369,1.172],[43.213,-3.223],[51.172,-15.576],[42.09,-16.699]],"c":true},"ix":2},"nm":"e","mn":"ADBE Vector Shape - Group","hd":false},{"ind":1,"ty":"sh","ix":2,"ks":{"a":0,"k":{"i":[[-2.751,2.702],[-4.037,0],[-2.8,-3.385],[-0.391,-4.362],[0,0]],"o":[[2.75,-2.702],[4.459,0],[1.823,2.181],[0,0],[0.293,-4.524]],"v":[[17.798,-41.748],[27.979,-45.801],[38.867,-40.723],[42.188,-30.908],[13.232,-30.908]],"c":true},"ix":2},"nm":"e","mn":"ADBE Vector Shape - Group","hd":false}],"nm":"e","np":5,"cix":2,"ix":1,"mn":"ADBE Vector Group","hd":false}]},"fFamily":"Arial"},{"ch":"a","size":12,"style":"Regular","w":55.62,"data":{"shapes":[{"ty":"gr","it":[{"ind":0,"ty":"sh","ix":1,"ks":{"a":0,"k":{"i":[[-0.912,-1.823],[0,0],[0.374,2.165],[0,8.171],[0,0],[0.293,1.498],[1.302,1.579],[2.766,1.042],[4.427,0],[3.385,-1.221],[1.79,-2.262],[0.781,-3.678],[0,0],[-1.97,1.449],[-4.134,0],[-2.246,-1.985],[0,-3.58],[0.032,-1.204],[7.096,-0.846],[1.725,-0.455],[1.871,-1.27],[1.155,-2.1],[0,-2.539],[-3.06,-2.783],[-5.697,0],[-3.011,1.139],[-3.255,2.767]],"o":[[0,0],[-1.107,-1.985],[-0.375,-2.164],[0,0],[0,-3.906],[-0.521,-2.409],[-1.302,-1.579],[-2.767,-1.041],[-4.46,0],[-3.386,1.221],[-1.791,2.263],[0,0],[0.944,-3.678],[1.969,-1.448],[4.427,0],[1.66,1.465],[0,0.326],[-3.353,1.172],[-3.484,0.423],[-2.344,0.652],[-1.872,1.27],[-1.156,2.1],[0,4.33],[3.059,2.783],[3.45,0],[3.011,-1.139],[0.26,2.441]],"v":[[42.188,0],[51.367,0],[49.146,-6.226],[48.584,-21.729],[48.584,-33.447],[48.145,-41.553],[45.41,-47.534],[39.307,-51.465],[28.516,-53.027],[16.748,-51.196],[8.984,-45.972],[5.127,-37.061],[13.721,-35.889],[18.091,-43.579],[27.246,-45.752],[37.256,-42.773],[39.746,-35.205],[39.697,-32.91],[24.023,-29.883],[16.211,-28.564],[9.888,-25.684],[5.347,-20.63],[3.613,-13.672],[8.203,-3.003],[21.338,1.172],[31.03,-0.537],[40.43,-6.396]],"c":true},"ix":2},"nm":"a","mn":"ADBE Vector Shape - Group","hd":false},{"ind":1,"ty":"sh","ix":2,"ks":{"a":0,"k":{"i":[[0,0],[0.944,-1.985],[2.637,-1.481],[3.385,0],[1.774,1.562],[0,2.344],[-0.814,1.254],[-1.498,0.652],[-3.613,0.521],[-3.191,1.302]],"o":[[0,3.874],[-1.237,2.572],[-2.637,1.482],[-3.418,0],[-1.775,-1.562],[0,-1.53],[0.813,-1.253],[1.497,-0.651],[6.38,-0.911],[0,0]],"v":[[39.697,-22.803],[38.281,-14.014],[32.471,-7.935],[23.438,-5.713],[15.649,-8.057],[12.988,-13.916],[14.209,-18.091],[17.676,-20.947],[25.342,-22.705],[39.697,-26.025]],"c":true},"ix":2},"nm":"a","mn":"ADBE Vector Shape - Group","hd":false}],"nm":"a","np":5,"cix":2,"ix":1,"mn":"ADBE Vector Group","hd":false}]},"fFamily":"Arial"},{"ch":"r","size":12,"style":"Regular","w":33.3,"data":{"shapes":[{"ty":"gr","it":[{"ind":0,"ty":"sh","ix":1,"ks":{"a":0,"k":{"i":[[0,0],[0,0],[-0.977,3.125],[-1.53,1.156],[-1.921,0],[-2.148,-1.27],[0,0],[2.962,0],[1.709,-1.172],[2.018,-3.678],[0,0],[0,0],[0,0]],"o":[[0,0],[0,-3.711],[0.651,-2.051],[1.53,-1.155],[2.148,0],[0,0],[-3.06,-1.888],[-2.051,0],[-1.709,1.172],[0,0],[0,0],[0,0],[0,0]],"v":[[15.283,0],[15.283,-27.148],[16.748,-37.402],[20.02,-42.212],[25.195,-43.945],[31.641,-42.041],[34.668,-50.195],[25.635,-53.027],[19.995,-51.27],[14.404,-43.994],[14.404,-51.855],[6.494,-51.855],[6.494,0]],"c":true},"ix":2},"nm":"r","mn":"ADBE Vector Shape - Group","hd":false}],"nm":"r","np":3,"cix":2,"ix":1,"mn":"ADBE Vector Group","hd":false}]},"fFamily":"Arial"},{"ch":"t","size":12,"style":"Regular","w":27.78,"data":{"shapes":[{"ty":"gr","it":[{"ind":0,"ty":"sh","ix":1,"ks":{"a":0,"k":{"i":[[0.977,0],[0.7,0.423],[0.309,0.716],[0,2.507],[0,0],[0,0],[0,0],[0,0],[0,0],[0,0],[0,0],[0,0],[0,0],[0,0],[0,0],[-0.716,-1.643],[-1.758,-1.009],[-3.191,0],[-2.474,0.52],[0,0]],"o":[[-1.302,0],[-0.7,-0.423],[-0.31,-0.716],[0,0],[0,0],[0,0],[0,0],[0,0],[0,0],[0,0],[0,0],[0,0],[0,0],[0,0],[0,5.273],[0.716,1.644],[1.758,1.009],[1.953,0],[0,0],[-1.595,0.228]],"v":[[21.924,-7.52],[18.921,-8.154],[17.407,-9.863],[16.943,-14.697],[16.943,-45.02],[25.781,-45.02],[25.781,-51.855],[16.943,-51.855],[16.943,-69.971],[8.203,-64.697],[8.203,-51.855],[1.758,-51.855],[1.758,-45.02],[8.203,-45.02],[8.203,-15.186],[9.277,-4.81],[12.988,-0.83],[20.41,0.684],[27.051,-0.098],[25.781,-7.861]],"c":true},"ix":2},"nm":"t","mn":"ADBE Vector Shape - Group","hd":false}],"nm":"t","np":3,"cix":2,"ix":1,"mn":"ADBE Vector Group","hd":false}]},"fFamily":"Arial"},{"ch":" ","size":12,"style":"Regular","w":27.78,"data":{},"fFamily":"Arial"},{"ch":"f","size":12,"style":"Regular","w":25.98,"data":{"shapes":[{"ty":"gr","it":[{"ind":0,"ty":"sh","ix":1,"ks":{"a":0,"k":{"i":[[0,0],[0,0],[0,0],[0,0],[0,0],[0,0],[-1.107,1.14],[-2.67,0],[-1.823,-0.325],[0,0],[2.473,0],[2.132,-1.416],[0.846,-2.278],[0,-3.483],[0,0],[0,0],[0,0],[0,0],[0,0]],"o":[[0,0],[0,0],[0,0],[0,0],[0,0],[0,-3.125],[1.106,-1.139],[1.627,0],[0,0],[-2.995,-0.586],[-3.841,0],[-2.132,1.416],[-0.619,1.693],[0,0],[0,0],[0,0],[0,0],[0,0],[0,0]],"v":[[17.432,0],[17.432,-45.02],[27.539,-45.02],[27.539,-51.855],[17.432,-51.855],[17.432,-56.641],[19.092,-63.037],[24.756,-64.746],[29.932,-64.258],[31.25,-71.924],[23.047,-72.803],[14.087,-70.679],[9.619,-65.137],[8.691,-57.373],[8.691,-51.855],[0.928,-51.855],[0.928,-45.02],[8.691,-45.02],[8.691,0]],"c":true},"ix":2},"nm":"f","mn":"ADBE Vector Shape - Group","hd":false}],"nm":"f","np":3,"cix":2,"ix":1,"mn":"ADBE Vector Group","hd":false}]},"fFamily":"Arial"},{"ch":"i","size":12,"style":"Regular","w":22.22,"data":{"shapes":[{"ty":"gr","it":[{"ind":0,"ty":"sh","ix":1,"ks":{"a":0,"k":{"i":[[0,0],[0,0],[0,0],[0,0]],"o":[[0,0],[0,0],[0,0],[0,0]],"v":[[15.43,-61.475],[15.43,-71.582],[6.641,-71.582],[6.641,-61.475]],"c":true},"ix":2},"nm":"i","mn":"ADBE Vector Shape - Group","hd":false},{"ind":1,"ty":"sh","ix":2,"ks":{"a":0,"k":{"i":[[0,0],[0,0],[0,0],[0,0]],"o":[[0,0],[0,0],[0,0],[0,0]],"v":[[15.43,0],[15.43,-51.855],[6.641,-51.855],[6.641,0]],"c":true},"ix":2},"nm":"i","mn":"ADBE Vector Shape - Group","hd":false}],"nm":"i","np":5,"cix":2,"ix":1,"mn":"ADBE Vector Group","hd":false}]},"fFamily":"Arial"},{"ch":"l","size":12,"style":"Regular","w":22.22,"data":{"shapes":[{"ty":"gr","it":[{"ind":0,"ty":"sh","ix":1,"ks":{"a":0,"k":{"i":[[0,0],[0,0],[0,0],[0,0]],"o":[[0,0],[0,0],[0,0],[0,0]],"v":[[15.186,0],[15.186,-71.582],[6.396,-71.582],[6.396,0]],"c":true},"ix":2},"nm":"l","mn":"ADBE Vector Shape - Group","hd":false}],"nm":"l","np":3,"cix":2,"ix":1,"mn":"ADBE Vector Group","hd":false}]},"fFamily":"Arial"},{"ch":"u","size":12,"style":"Regular","w":55.62,"data":{"shapes":[{"ty":"gr","it":[{"ind":0,"ty":"sh","ix":1,"ks":{"a":0,"k":{"i":[[0,0],[0,0],[0,0],[0,0],[0.96,-2.327],[2.311,-1.35],[2.637,0],[1.79,1.318],[0.553,2.312],[0,4.59],[0,0],[0,0],[0,0],[-0.359,-1.725],[-1.286,-1.774],[-2.654,-1.172],[-3.06,0],[-4.037,5.859],[0,0]],"o":[[0,0],[0,0],[0,0],[0,4.427],[-0.961,2.328],[-2.312,1.351],[-2.637,0],[-1.791,-1.318],[-0.359,-1.595],[0,0],[0,0],[0,0],[0,3.744],[0.52,2.572],[1.286,1.775],[2.653,1.172],[6.934,0],[0,0],[0,0]],"v":[[48.438,0],[48.438,-51.855],[39.648,-51.855],[39.648,-24.072],[38.208,-13.94],[33.301,-8.423],[25.879,-6.396],[19.238,-8.374],[15.723,-13.818],[15.186,-23.096],[15.186,-51.855],[6.396,-51.855],[6.396,-19.727],[6.934,-11.523],[9.644,-5.005],[15.552,-0.586],[24.121,1.172],[40.576,-7.617],[40.576,0]],"c":true},"ix":2},"nm":"u","mn":"ADBE Vector Shape - Group","hd":false}],"nm":"u","np":3,"cix":2,"ix":1,"mn":"ADBE Vector Group","hd":false}]},"fFamily":"Arial"}]}